rusta_tools/__init__.py
rusta_tools/db_config.json
rusta_tools/query_loader.py
rusta_tools/snowflake_connection.py
rusta_tools-0.0.11.dist-info/METADATA
rusta_tools-0.0.11.dist-info/WHEEL
rusta_tools-0.0.11.dist-info/licenses/license
rusta_tools-0.0.11.dist-info/RECORD
