Metadata-Version: 2.4
Name: rusta_tools
Version: 0.0.11
Summary: Tools for scraping at Rusta
Author-email: David Momeni <dav.momeni@gmail.com>
License-File: license
Classifier: License :: OSI Approved :: MIT License
Classifier: Operating System :: OS Independent
Classifier: Programming Language :: Python :: 3
Requires-Python: >=3.8
